{
  "_metadata": {
    "timestamp": "2025-10-14T10:35:49.474Z",
    "version": "1.0",
    "checksum": "8085bad"
  },
  "data": {
    "paragraph": "asdfgh",
    "contact": {
      "phone": "0123456789",
      "phoneLink": "",
      "email": "dfghj@er.com",
      "emailLink": "",
      "address": "dubai",
      "addressLink": ""
    },
    "columns": {
      "services": {
        "heading": "Services",
        "items": []
      },
      "locations": {
        "heading": "Global Locations",
        "items": []
      },
      "resources": {
        "heading": "Resources",
        "items": []
      }
    },
    "bottom": {
      "copyright": "© 2024 StandsZone. All rights reserved.",
      "links": [
        {
          "label": "Privacy Policy",
          "href": "/legal/privacy-policy"
        },
        {
          "label": "Terms of Service",
          "href": "/legal/terms-of-service"
        },
        {
          "label": "Cookie Policy",
          "href": "/legal/cookie-policy"
        }
      ]
    },
    "social": [
      {
        "label": "LinkedIn",
        "href": "#",
        "icon": "linkedin"
      },
      {
        "label": "Twitter",
        "href": "#",
        "icon": "twitter"
      },
      {
        "label": "Instagram",
        "href": "#",
        "icon": "instagram"
      },
      {
        "label": "Facebook",
        "href": "#",
        "icon": "facebook"
      }
    ],
    "updatedAt": "2025-10-14T10:35:49.473Z"
  }
}